argparse_logging.py
argparse_logging-2020.11.26.dist-info/METADATA
argparse_logging-2020.11.26.dist-info/WHEEL
argparse_logging-2020.11.26.dist-info/top_level.txt
argparse_logging-2020.11.26.dist-info/RECORD
