Metadata-Version: 2.1
Name: argparse-logging
Version: 2020.11.26
Summary: This is a simple library to configure logging from command line argument when using argparse.
Home-page: https://github.com/nanassito/argparse_logging
Author: Dorian Jaminais
Author-email: argparse_logging@jaminais.fr
License: UNKNOWN
Platform: UNKNOWN
Classifier: Programming Language :: Python :: 3
Classifier: License :: Public Domain
Classifier: Operating System :: OS Independent
Requires-Python: >=3.6
